pynitrokey/VERSION
pynitrokey/__init__.py
pynitrokey/confconsts.py
pynitrokey/exceptions.py
pynitrokey/helpers.py
pynitrokey/libnk.py
pynitrokey/cli/__init__.py
pynitrokey/cli/_patches.py
pynitrokey/cli/fido2.py
pynitrokey/cli/monitor.py
pynitrokey/cli/nethsm.py
pynitrokey/cli/program.py
pynitrokey/cli/start.py
pynitrokey/cli/storage.py
pynitrokey/cli/update.py
pynitrokey/fido2/__init__.py
pynitrokey/fido2/client.py
pynitrokey/fido2/commands.py
pynitrokey/fido2/dfu.py
pynitrokey/fido2/enums.py
pynitrokey/fido2/hmac_secret.py
pynitrokey/fido2/operations.py
pynitrokey/nethsm/__init__.py
pynitrokey/nethsm/client/__init__.py
pynitrokey/nethsm/client/api_client.py
pynitrokey/nethsm/client/configuration.py
pynitrokey/nethsm/client/exceptions.py
pynitrokey/nethsm/client/model_utils.py
pynitrokey/nethsm/client/rest.py
pynitrokey/nethsm/client/api/__init__.py
pynitrokey/nethsm/client/api/default_api.py
pynitrokey/nethsm/client/apis/__init__.py
pynitrokey/nethsm/client/model/__init__.py
pynitrokey/nethsm/client/model/backup_passphrase_config.py
pynitrokey/nethsm/client/model/base64.py
pynitrokey/nethsm/client/model/decrypt_data.py
pynitrokey/nethsm/client/model/decrypt_mode.py
pynitrokey/nethsm/client/model/decrypt_request_data.py
pynitrokey/nethsm/client/model/distinguished_name.py
pynitrokey/nethsm/client/model/health_state_data.py
pynitrokey/nethsm/client/model/id.py
pynitrokey/nethsm/client/model/info_data.py
pynitrokey/nethsm/client/model/key_algorithm.py
pynitrokey/nethsm/client/model/key_generate_request_data.py
pynitrokey/nethsm/client/model/key_item.py
pynitrokey/nethsm/client/model/key_list.py
pynitrokey/nethsm/client/model/key_mechanism.py
pynitrokey/nethsm/client/model/key_mechanisms.py
pynitrokey/nethsm/client/model/key_private_data.py
pynitrokey/nethsm/client/model/key_public_data.py
pynitrokey/nethsm/client/model/log_level.py
pynitrokey/nethsm/client/model/logging_config.py
pynitrokey/nethsm/client/model/network_config.py
pynitrokey_debug-0.4.10.dist-info/entry_points.txt
pynitrokey_debug-0.4.10.dist-info/LICENSE-APACHE
pynitrokey_debug-0.4.10.dist-info/LICENSE-MIT
pynitrokey_debug-0.4.10.dist-info/WHEEL
pynitrokey_debug-0.4.10.dist-info/METADATA
pynitrokey_debug-0.4.10.dist-info/RECORD
