Metadata-Version: 2.1
Name: pynitrokey-debug
Version: 0.4.10
Summary: Python Library for Nitrokey FIDO2 & Nitrokey Start.
Home-page: https://github.com/Nitrokey/pynitrokey
Author: Nitrokey
Author-email: pypi@nitrokey.com
Requires-Python: >=3.6
Classifier: License :: OSI Approved :: MIT License
Classifier: License :: OSI Approved :: Apache Software License
Classifier: Intended Audience :: Developers
Classifier: Intended Audience :: End Users/Desktop
Classifier: Programming Language :: Python :: 3 :: Only
Classifier: Programming Language :: Python :: 3.6
Classifier: Programming Language :: Python :: 3.7
Requires-Dist: click >= 7.0
Requires-Dist: cryptography
Requires-Dist: ecdsa
Requires-Dist: fido2 == 0.8.1
Requires-Dist: intelhex
Requires-Dist: pyserial
Requires-Dist: pyusb
Requires-Dist: requests
Requires-Dist: pygments
Requires-Dist: python-dateutil
Requires-Dist: urllib3
Requires-Dist: cffi
Requires-Dist: cbor
